Workbook

Sheet KPI Dashboard
A1: 📊 SALES REVENUE & EXPENSE DASHBOARD — FISCAL YEAR 2024
A2: RetailCo Inc. | All Regions | Electronics · Furniture · Appliances | January – December 2024
A4: 💰 TOTAL REVENUE | E4: 💸 TOTAL EXPENSES | I4: 📈 GROSS PROFIT | M4: 🎯 AVG PROFIT MARGIN
A5: ='Monthly Summary'!B17 -> 5008000 | E5: ='Monthly Summary'!C17 -> 3096000 | I5: ='Monthly Summary'!D17 -> 1912000 | M5: ='Monthly Summary'!E17 -> 0.38178914
A7: vs. Prior Target ↑ | E7: vs. Prior Target ↑ | I7: vs. Prior Target ↑ | M7: vs. Prior Target ↑
A8: ✅ Revenue vs Target: All Months | E8: 📦 Total Units Sold | I8: 🏆 Best Month (Revenue) | M8: 📉 Lowest Margin Month
A9: ='Monthly Summary'!G17 -> 122000 | E9: =SUMPRODUCT(('Raw Data'!B2:B1000>0)*'Raw Data'!G2:G1000) -> 25035 | I9: =INDEX('Monthly Summary'!A5:A16,MATCH(MAX('Monthly Summary'!B5:B16),'Monthly Summary'!B5:B16,0)) -> December | M9: =INDEX('Monthly Summary'!A5:A16,MATCH(MIN('Monthly Summary'!E5:E16),'Monthly Summary'!E5:E16,0)) -> January
A12: MONTHLY REVENUE vs EXPENSES vs TARGET | I12: PROFIT MARGIN BY MONTH (%)
A32: PERFORMANCE SUMMARY BY CATEGORY
A33: Chart Data — Monthly
A34: Month | B34: Revenue | C34: Expenses | D34: Target | E34: Profit Margin
A35: January | B35: ='Monthly Summary'!B5 -> 299000 | C35: ='Monthly Summary'!C5 -> 187000 | D35: ='Monthly Summary'!F5 -> 300000 | E35: ='Monthly Summary'!E5 -> 0.37458194
A36: February | B36: ='Monthly Summary'!B6 -> 313000 | C36: ='Monthly Summary'!C6 -> 195000 | D36: ='Monthly Summary'!F6 -> 314000 | E36: ='Monthly Summary'!E6 -> 0.37699681
A37: March | B37: ='Monthly Summary'!B7 -> 352000 | C37: ='Monthly Summary'!C7 -> 218000 | D37: ='Monthly Summary'!F7 -> 339000 | E37: ='Monthly Summary'!E7 -> 0.38068182
A38: April | B38: ='Monthly Summary'!B8 -> 376000 | C38: ='Monthly Summary'!C8 -> 233000 | D38: ='Monthly Summary'!F8 -> 361000 | E38: ='Monthly Summary'!E8 -> 0.38031915
A39: May | B39: ='Monthly Summary'!B9 -> 404000 | C39: ='Monthly Summary'!C9 -> 249000 | D39: ='Monthly Summary'!F9 -> 390000 | E39: ='Monthly Summary'!E9 -> 0.38366337
A40: June | B40: ='Monthly Summary'!B10 -> 429000 | C40: ='Monthly Summary'!C10 -> 265000 | D40: ='Monthly Summary'!F10 -> 416000 | E40: ='Monthly Summary'!E10 -> 0.38228438
A41: July | B41: ='Monthly Summary'!B11 -> 393000 | C41: ='Monthly Summary'!C11 -> 244000 | D41: ='Monthly Summary'!F11 -> 409000 | E41: ='Monthly Summary'!E11 -> 0.37913486
A42: August | B42: ='Monthly Summary'!B12 -> 418000 | C42: ='Monthly Summary'!C12 -> 259000 | D42: ='Monthly Summary'!F12 -> 408000 | E42: ='Monthly Summary'!E12 -> 0.38038278
A43: September | B43: ='Monthly Summary'!B13 -> 447000 | C43: ='Monthly Summary'!C13 -> 275000 | D43: ='Monthly Summary'!F13 -> 432000 | E43: ='Monthly Summary'!E13 -> 0.38478747
A44: October | B44: ='Monthly Summary'!B14 -> 478000 | C44: ='Monthly Summary'!C14 -> 294000 | D44: ='Monthly Summary'!F14 -> 461000 | E44: ='Monthly Summary'!E14 -> 0.38493724
A45: November | B45: ='Monthly Summary'!B15 -> 524000 | C45: ='Monthly Summary'!C15 -> 323000 | D45: ='Monthly Summary'!F15 -> 504000 | E45: ='Monthly Summary'!E15 -> 0.38358779
A46: December | B46: ='Monthly Summary'!B16 -> 575000 | C46: ='Monthly Summary'!C16 -> 354000 | D46: ='Monthly Summary'!F16 -> 552000 | E46: ='Monthly Summary'!E16 -> 0.38434783
A48: Category | B48: Revenue | C48: Expenses | D48: Gross Profit | E48: Margin % | H48: Region | I48: Revenue | J48: Expenses | K48: Gross Profit | L48: Margin %
A49: ='Category & Region'!A5 -> Electronics | B49: ='Category & Region'!B5 -> 2419000 | C49: ='Category & Region'!C5 -> 1470000 | D49: ='Category & Region'!D5 -> 949000 | E49: ='Category & Region'!E5 -> 0.39231087 | H49: ='Category & Region'!A12 -> North | I49: ='Category & Region'!B12 -> 2571000 | J49: ='Category & Region'!C12 -> 1562000 | K49: ='Category & Region'!D12 -> 1009000 | L49: ='Category & Region'!E12 -> 0.3924543
A50: ='Category & Region'!A6 -> Furniture | B50: ='Category & Region'!B6 -> 1406000 | C50: ='Category & Region'!C6 -> 899000 | D50: ='Category & Region'!D6 -> 507000 | E50: ='Category & Region'!E6 -> 0.36059744 | H50: ='Category & Region'!A13 -> South | I50: ='Category & Region'!B13 -> 1031000 | J50: ='Category & Region'!C13 -> 635000 | K50: ='Category & Region'!D13 -> 396000 | L50: ='Category & Region'!E13 -> 0.38409311
A51: ='Category & Region'!A7 -> Appliances | B51: ='Category & Region'!B7 -> 1183000 | C51: ='Category & Region'!C7 -> 727000 | D51: ='Category & Region'!D7 -> 456000 | E51: ='Category & Region'!E7 -> 0.38546069 | H51: ='Category & Region'!A14 -> East | I51: ='Category & Region'!B14 -> 746000 | J51: ='Category & Region'!C14 -> 472000 | K51: ='Category & Region'!D14 -> 274000 | L51: ='Category & Region'!E14 -> 0.36729223
H52: ='Category & Region'!A15 -> West | I52: ='Category & Region'!B15 -> 660000 | J52: ='Category & Region'!C15 -> 427000 | K52: ='Category & Region'!D15 -> 233000 | L52: ='Category & Region'!E15 -> 0.3530303

Sheet Raw Data
A1: Month | B1: Month_Num | C1: Region | D1: Category | E1: Revenue ($) | F1: Expenses ($) | G1: Units Sold | H1: Revenue Target ($) | I1: Profit ($) | J1: Profit Margin (%) | K1: vs Target ($) | L1: vs Target (%)
A2: January | B2: 1 | C2: North | D2: Electronics | E2: 85000 | F2: 52000 | G2: 420 | H2: 80000 | I2: =E2-F2 -> 33000 | J2: =IF(E2>0,I2/E2,0) -> 0.38823529 | K2: =E2-H2 -> 5000 | L2: =IF(H2>0,K2/H2,0) -> 0.0625
A3: January | B3: 1 | C3: South | D3: Electronics | E3: 62000 | F3: 38000 | G3: 310 | H3: 65000 | I3: =E3-F3 -> 24000 | J3: =IF(E3>0,I3/E3,0) -> 0.38709677 | K3: =E3-H3 -> -3000 | L3: =IF(H3>0,K3/H3,0) -> -0.046153846
A4: January | B4: 1 | C4: East | D4: Furniture | E4: 43000 | F4: 28000 | G4: 215 | H4: 45000 | I4: =E4-F4 -> 15000 | J4: =IF(E4>0,I4/E4,0) -> 0.34883721 | K4: =E4-H4 -> -2000 | L4: =IF(H4>0,K4/H4,0) -> -0.044444444
A5: January | B5: 1 | C5: West | D5: Furniture | E5: 38000 | F5: 25000 | G5: 190 | H5: 40000 | I5: =E5-F5 -> 13000 | J5: =IF(E5>0,I5/E5,0) -> 0.34210526 | K5: =E5-H5 -> -2000 | L5: =IF(H5>0,K5/H5,0) -> -0.05
A6: January | B6: 1 | C6: North | D6: Appliances | E6: 71000 | F6: 44000 | G6: 355 | H6: 70000 | I6: =E6-F6 -> 27000 | J6: =IF(E6>0,I6/E6,0) -> 0.38028169 | K6: =E6-H6 -> 1000 | L6: =IF(H6>0,K6/H6,0) -> 0.014285714
A7: February | B7: 2 | C7: North | D7: Electronics | E7: 91000 | F7: 55000 | G7: 455 | H7: 88000 | I7: =E7-F7 -> 36000 | J7: =IF(E7>0,I7/E7,0) -> 0.3956044 | K7: =E7-H7 -> 3000 | L7: =IF(H7>0,K7/H7,0) -> 0.034090909
A8: February | B8: 2 | C8: South | D8: Electronics | E8: 58000 | F8: 36000 | G8: 290 | H8: 62000 | I8: =E8-F8 -> 22000 | J8: =IF(E8>0,I8/E8,0) -> 0.37931034 | K8: =E8-H8 -> -4000 | L8: =IF(H8>0,K8/H8,0) -> -0.064516129
A9: February | B9: 2 | C9: East | D9: Furniture | E9: 47000 | F9: 30000 | G9: 235 | H9: 48000 | I9: =E9-F9 -> 17000 | J9: =IF(E9>0,I9/E9,0) -> 0.36170213 | K9: =E9-H9 -> -1000 | L9: =IF(H9>0,K9/H9,0) -> -0.020833333
A10: February | B10: 2 | C10: West | D10: Furniture | E10: 41000 | F10: 27000 | G10: 205 | H10: 42000 | I10: =E10-F10 -> 14000 | J10: =IF(E10>0,I10/E10,0) -> 0.34146341 | K10: =E10-H10 -> -1000 | L10: =IF(H10>0,K10/H10,0) -> -0.023809524
A11: February | B11: 2 | C11: North | D11: Appliances | E11: 76000 | F11: 47000 | G11: 380 | H11: 74000 | I11: =E11-F11 -> 29000 | J11: =IF(E11>0,I11/E11,0) -> 0.38157895 | K11: =E11-H11 -> 2000 | L11: =IF(H11>0,K11/H11,0) -> 0.027027027
A12: March | B12: 3 | C12: North | D12: Electronics | E12: 98000 | F12: 59000 | G12: 490 | H12: 95000 | I12: =E12-F12 -> 39000 | J12: =IF(E12>0,I12/E12,0) -> 0.39795918 | K12: =E12-H12 -> 3000 | L12: =IF(H12>0,K12/H12,0) -> 0.031578947
A13: March | B13: 3 | C13: South | D13: Electronics | E13: 73000 | F13: 45000 | G13: 365 | H13: 70000 | I13: =E13-F13 -> 28000 | J13: =IF(E13>0,I13/E13,0) -> 0.38356164 | K13: =E13-H13 -> 3000 | L13: =IF(H13>0,K13/H13,0) -> 0.042857143
... A61: December | B61: 12 | C61: North | D61: Appliances | E61: 134000 | F61: 82000 | G61: 670 | H61: 129000 | I61: =E61-F61 -> 52000 | J61: =IF(E61>0,I61/E61,0) -> 0.3880597 | K61: =E61-H61 -> 5000 | L61: =IF(H61>0,K61/H61,0) -> 0.03875969

Sheet Monthly Summary
A1: Monthly Revenue & Performance Summary
A2: RetailCo Inc. | Fiscal Year 2024 | All Regions & Categories
A4: Month | B4: Total Revenue | C4: Total Expenses | D4: Gross Profit | E4: Profit Margin | F4: Revenue Target | G4: vs Target ($) | H4: vs Target (%)
A5: January | B5: =SUMIF('Raw Data'!B:B,1,'Raw Data'!E:E) -> 299000 | C5: =SUMIF('Raw Data'!B:B,1,'Raw Data'!F:F) -> 187000 | D5: =B5-C5 -> 112000 | E5: =IF(B5>0,D5/B5,0) -> 0.37458194 | F5: =SUMIF('Raw Data'!B:B,1,'Raw Data'!H:H) -> 300000 | G5: =B5-F5 -> -1000 | H5: =IF(F5>0,G5/F5,0) -> -0.0033333333
A6: February | B6: =SUMIF('Raw Data'!B:B,2,'Raw Data'!E:E) -> 313000 | C6: =SUMIF('Raw Data'!B:B,2,'Raw Data'!F:F) -> 195000 | D6: =B6-C6 -> 118000 | E6: =IF(B6>0,D6/B6,0) -> 0.37699681 | F6: =SUMIF('Raw Data'!B:B,2,'Raw Data'!H:H) -> 314000 | G6: =B6-F6 -> -1000 | H6: =IF(F6>0,G6/F6,0) -> -0.0031847134
A7: March | B7: =SUMIF('Raw Data'!B:B,3,'Raw Data'!E:E) -> 352000 | C7: =SUMIF('Raw Data'!B:B,3,'Raw Data'!F:F) -> 218000 | D7: =B7-C7 -> 134000 | E7: =IF(B7>0,D7/B7,0) -> 0.38068182 | F7: =SUMIF('Raw Data'!B:B,3,'Raw Data'!H:H) -> 339000 | G7: =B7-F7 -> 13000 | H7: =IF(F7>0,G7/F7,0) -> 0.038348083
A8: April | B8: =SUMIF('Raw Data'!B:B,4,'Raw Data'!E:E) -> 376000 | C8: =SUMIF('Raw Data'!B:B,4,'Raw Data'!F:F) -> 233000 | D8: =B8-C8 -> 143000 | E8: =IF(B8>0,D8/B8,0) -> 0.38031915 | F8: =SUMIF('Raw Data'!B:B,4,'Raw Data'!H:H) -> 361000 | G8: =B8-F8 -> 15000 | H8: =IF(F8>0,G8/F8,0) -> 0.041551247
A9: May | B9: =SUMIF('Raw Data'!B:B,5,'Raw Data'!E:E) -> 404000 | C9: =SUMIF('Raw Data'!B:B,5,'Raw Data'!F:F) -> 249000 | D9: =B9-C9 -> 155000 | E9: =IF(B9>0,D9/B9,0) -> 0.38366337 | F9: =SUMIF('Raw Data'!B:B,5,'Raw Data'!H:H) -> 390000 | G9: =B9-F9 -> 14000 | H9: =IF(F9>0,G9/F9,0) -> 0.035897436
A10: June | B10: =SUMIF('Raw Data'!B:B,6,'Raw Data'!E:E) -> 429000 | C10: =SUMIF('Raw Data'!B:B,6,'Raw Data'!F:F) -> 265000 | D10: =B10-C10 -> 164000 | E10: =IF(B10>0,D10/B10,0) -> 0.38228438 | F10: =SUMIF('Raw Data'!B:B,6,'Raw Data'!H:H) -> 416000 | G10: =B10-F10 -> 13000 | H10: =IF(F10>0,G10/F10,0) -> 0.03125
A11: July | B11: =SUMIF('Raw Data'!B:B,7,'Raw Data'!E:E) -> 393000 | C11: =SUMIF('Raw Data'!B:B,7,'Raw Data'!F:F) -> 244000 | D11: =B11-C11 -> 149000 | E11: =IF(B11>0,D11/B11,0) -> 0.37913486 | F11: =SUMIF('Raw Data'!B:B,7,'Raw Data'!H:H) -> 409000 | G11: =B11-F11 -> -16000 | H11: =IF(F11>0,G11/F11,0) -> -0.039119804
A12: August | B12: =SUMIF('Raw Data'!B:B,8,'Raw Data'!E:E) -> 418000 | C12: =SUMIF('Raw Data'!B:B,8,'Raw Data'!F:F) -> 259000 | D12: =B12-C12 -> 159000 | E12: =IF(B12>0,D12/B12,0) -> 0.38038278 | F12: =SUMIF('Raw Data'!B:B,8,'Raw Data'!H:H) -> 408000 | G12: =B12-F12 -> 10000 | H12: =IF(F12>0,G12/F12,0) -> 0.024509804
A13: September | B13: =SUMIF('Raw Data'!B:B,9,'Raw Data'!E:E) -> 447000 | C13: =SUMIF('Raw Data'!B:B,9,'Raw Data'!F:F) -> 275000 | D13: =B13-C13 -> 172000 | E13: =IF(B13>0,D13/B13,0) -> 0.38478747 | F13: =SUMIF('Raw Data'!B:B,9,'Raw Data'!H:H) -> 432000 | G13: =B13-F13 -> 15000 | H13: =IF(F13>0,G13/F13,0) -> 0.034722222
A14: October | B14: =SUMIF('Raw Data'!B:B,10,'Raw Data'!E:E) -> 478000 | C14: =SUMIF('Raw Data'!B:B,10,'Raw Data'!F:F) -> 294000 | D14: =B14-C14 -> 184000 | E14: =IF(B14>0,D14/B14,0) -> 0.38493724 | F14: =SUMIF('Raw Data'!B:B,10,'Raw Data'!H:H) -> 461000 | G14: =B14-F14 -> 17000 | H14: =IF(F14>0,G14/F14,0) -> 0.036876356
A15: November | B15: =SUMIF('Raw Data'!B:B,11,'Raw Data'!E:E) -> 524000 | C15: =SUMIF('Raw Data'!B:B,11,'Raw Data'!F:F) -> 323000 | D15: =B15-C15 -> 201000 | E15: =IF(B15>0,D15/B15,0) -> 0.38358779 | F15: =SUMIF('Raw Data'!B:B,11,'Raw Data'!H:H) -> 504000 | G15: =B15-F15 -> 20000 | H15: =IF(F15>0,G15/F15,0) -> 0.03968254
A16: December | B16: =SUMIF('Raw Data'!B:B,12,'Raw Data'!E:E) -> 575000 | C16: =SUMIF('Raw Data'!B:B,12,'Raw Data'!F:F) -> 354000 | D16: =B16-C16 -> 221000 | E16: =IF(B16>0,D16/B16,0) -> 0.38434783 | F16: =SUMIF('Raw Data'!B:B,12,'Raw Data'!H:H) -> 552000 | G16: =B16-F16 -> 23000 | H16: =IF(F16>0,G16/F16,0) -> 0.041666667
A17: FULL YEAR TOTAL | B17: =SUM(B5:B16) -> 5008000 | C17: =SUM(C5:C16) -> 3096000 | D17: =SUM(D5:D16) -> 1912000 | E17: =IF(B17>0,D17/B17,0) -> 0.38178914 | F17: =SUM(F5:F16) -> 4886000 | G17: =SUM(G5:G16) -> 122000 | H17: =IF(F17>0,G17/F17,0) -> 0.0249693
A19: Month-over-Month Revenue Growth
A20: Month | B20: Revenue | C20: Prior Month | D20: MoM Change ($) | E20: MoM Growth %
A21: January | B21: =B9 -> 404000 | C21: — | D21: — | E21: —
A22: February | B22: =B10 -> 429000 | C22: =B21 -> 404000 | D22: =B22-C22 -> 25000 | E22: =IF(C22>0,(B22-C22)/C22,0) -> 0.061881188
A23: March | B23: =B11 -> 393000 | C23: =B22 -> 429000 | D23: =B23-C23 -> -36000 | E23: =IF(C23>0,(B23-C23)/C23,0) -> -0.083916084
A24: April | B24: =B12 -> 418000 | C24: =B23 -> 393000 | D24: =B24-C24 -> 25000 | E24: =IF(C24>0,(B24-C24)/C24,0) -> 0.063613232
A25: May | B25: =B13 -> 447000 | C25: =B24 -> 418000 | D25: =B25-C25 -> 29000 | E25: =IF(C25>0,(B25-C25)/C25,0) -> 0.06937799
A26: June | B26: =B14 -> 478000 | C26: =B25 -> 447000 | D26: =B26-C26 -> 31000 | E26: =IF(C26>0,(B26-C26)/C26,0) -> 0.06935123
A27: July | B27: =B15 -> 524000 | C27: =B26 -> 478000 | D27: =B27-C27 -> 46000 | E27: =IF(C27>0,(B27-C27)/C27,0) -> 0.09623431
A28: August | B28: =B16 -> 575000 | C28: =B27 -> 524000 | D28: =B28-C28 -> 51000 | E28: =IF(C28>0,(B28-C28)/C28,0) -> 0.097328244
A29: September | B29: =B17 -> 5008000 | C29: =B28 -> 575000 | D29: =B29-C29 -> 4433000 | E29: =IF(C29>0,(B29-C29)/C29,0) -> 7.7095652
A30: October | B30: =B18 -> 0 | C30: =B29 -> 5008000 | D30: =B30-C30 -> -5008000 | E30: =IF(C30>0,(B30-C30)/C30,0) -> -1
A31: November | B31: =B19 -> 0 | C31: =B30 -> 0 | D31: =B31-C31 -> 0 | E31: =IF(C31>0,(B31-C31)/C31,0) -> 0
A32: December | B32: =B20 -> Revenue | C32: =B31 -> 0 | D32: — | E32: =IF(C32>0,(B32-C32)/C32,0) -> 0

Sheet Category & Region
A1: Revenue Breakdown by Category & Region
A3: By Category — Annual Revenue
A4: Category | B4: Total Revenue | C4: Total Expenses | D4: Gross Profit | E4: Avg Margin
A5: Electronics | B5: =SUMIF('Raw Data'!D:D,A5,'Raw Data'!E:E) -> 2419000 | C5: =SUMIF('Raw Data'!D:D,A5,'Raw Data'!F:F) -> 1470000 | D5: =B5-C5 -> 949000 | E5: =IF(B5>0,D5/B5,0) -> 0.39231087
A6: Furniture | B6: =SUMIF('Raw Data'!D:D,A6,'Raw Data'!E:E) -> 1406000 | C6: =SUMIF('Raw Data'!D:D,A6,'Raw Data'!F:F) -> 899000 | D6: =B6-C6 -> 507000 | E6: =IF(B6>0,D6/B6,0) -> 0.36059744
A7: Appliances | B7: =SUMIF('Raw Data'!D:D,A7,'Raw Data'!E:E) -> 1183000 | C7: =SUMIF('Raw Data'!D:D,A7,'Raw Data'!F:F) -> 727000 | D7: =B7-C7 -> 456000 | E7: =IF(B7>0,D7/B7,0) -> 0.38546069
A8: TOTAL | B8: =SUM(B5:B7) -> 5008000 | C8: =SUM(C5:C7) -> 3096000 | D8: =SUM(D5:D7) -> 1912000 | E8: =IF(B8>0,D8/B8,0) -> 0.38178914
A10: By Region — Annual Revenue
A11: Category | B11: Total Revenue | C11: Total Expenses | D11: Gross Profit | E11: Avg Margin
A12: North | B12: =SUMIF('Raw Data'!C:C,A12,'Raw Data'!E:E) -> 2571000 | C12: =SUMIF('Raw Data'!C:C,A12,'Raw Data'!F:F) -> 1562000 | D12: =B12-C12 -> 1009000 | E12: =IF(B12>0,D12/B12,0) -> 0.3924543
A13: South | B13: =SUMIF('Raw Data'!C:C,A13,'Raw Data'!E:E) -> 1031000 | C13: =SUMIF('Raw Data'!C:C,A13,'Raw Data'!F:F) -> 635000 | D13: =B13-C13 -> 396000 | E13: =IF(B13>0,D13/B13,0) -> 0.38409311
A14: East | B14: =SUMIF('Raw Data'!C:C,A14,'Raw Data'!E:E) -> 746000 | C14: =SUMIF('Raw Data'!C:C,A14,'Raw Data'!F:F) -> 472000 | D14: =B14-C14 -> 274000 | E14: =IF(B14>0,D14/B14,0) -> 0.36729223
A15: West | B15: =SUMIF('Raw Data'!C:C,A15,'Raw Data'!E:E) -> 660000 | C15: =SUMIF('Raw Data'!C:C,A15,'Raw Data'!F:F) -> 427000 | D15: =B15-C15 -> 233000 | E15: =IF(B15>0,D15/B15,0) -> 0.3530303
A16: TOTAL | B16: =SUM(B12:B15) -> 5008000 | C16: =SUM(C12:C15) -> 3096000 | D16: =SUM(D12:D15) -> 1912000 | E16: =IF(B16>0,D16/B16,0) -> 0.38178914
